MANIFEST.in
README.md
_snowboydetect.so
config.py
maison.service
maison.sh
mqtt_speak.py
setup.py
FSTA/__init__.py
FSTA/action.py
FSTA/cortical_language_analyser.py
FSTA/distance_syntaxique.py
FSTA/fred_language_analyser.py
FSTA/group.py
FSTA/installation.py
FSTA/language_analyser.py
FSTA/plugin.py
FSTA/scenario.py
FSTA.egg-info/PKG-INFO
FSTA.egg-info/SOURCES.txt
FSTA.egg-info/dependency_links.txt
FSTA.egg-info/requires.txt
FSTA.egg-info/top_level.txt
resources/Thumbs.db
resources/common.res
resources/distance_syntaxique.xlsx
resources/3D/FSTA_3D.skb
resources/3D/FSTA_3D.skp
resources/3D/FSTA_3D.stl
resources/3D/FSTA_3D_cover.stl
resources/3D/FSTA_3D_top.stl
resources/3D/pam8403-audio-amplifier.png
resources/Hotwords/Ok Kodi.pmdl
resources/Hotwords/maison.pmdl
resources/Hotwords/salon.pmdl
resources/Hotwords/snowboy.umdl
resources/hotwords/Ok Kodi.pmdl
resources/hotwords/alexa.umdl
resources/hotwords/maison.pmdl
resources/hotwords/salon.pmdl
resources/hotwords/snowboy.umdl
resources/rules/TV.scenario
resources/rules/cava.scenario
resources/rules/chuck.scenario
resources/rules/date.scenario
resources/rules/exemple.group
resources/rules/exemple.scenario
resources/rules/fuel.scenario
resources/rules/kodi.scenario
resources/rules/lumiere.scenario
resources/rules/maison.group
resources/rules/meteo.scenario
resources/rules/musique.scenario
resources/rules/stop.scenario
resources/rules/volume.scenario
resources/rules/volume_denon.scenario