Metadata-Version: 1.1
Name: FSTA
Version: 0.1.3
Summary: A python lib to Speech to Actions
Home-page: UNKNOWN
Author: FredThx
Author-email: FredThx@gmail.com
License: WTFPL
Platform: UNKNOWN
Classifier: Programming Language :: Python
Classifier: Development Status :: 4 - Beta
Classifier: License :: OSI Approved
Classifier: Natural Language :: French
Classifier: Operating System :: OS Independent
Classifier: Programming Language :: Python :: 2.7
